apt_repo_maker/__init__.py
apt_repo_maker/__main__.py
apt_repo_maker-3.0.0.dist-info/LICENSE
apt_repo_maker-3.0.0.dist-info/METADATA
apt_repo_maker-3.0.0.dist-info/WHEEL
apt_repo_maker-3.0.0.dist-info/entry_points.txt
apt_repo_maker-3.0.0.dist-info/RECORD
