Metadata-Version: 2.1
Name: apt-repo-maker
Version: 3.0.0
Summary: Host APT repos on GitHub
Home-page: https://github.com/zmarffy/apt-repo
License: MIT
Author: Zeke Marffy
Author-email: zmarffy@yahoo.com
Requires-Python: >=3.8.1,<4.0.0
Classifier: License :: OSI Approved :: MIT License
Classifier: Programming Language :: Python :: 3
Classifier: Programming Language :: Python :: 3.9
Classifier: Programming Language :: Python :: 3.10
Classifier: Programming Language :: Python :: 3.11
Requires-Dist: requests (>=2.31.0,<3.0.0)
Requires-Dist: rich (>=13.5.2,<14.0.0)
Requires-Dist: tabulate (>=0.9.0,<0.10.0)
Requires-Dist: zmtools (>=3.0.1,<4.0.0)
Project-URL: Repository, https://github.com/zmarffy/apt-repo
